switchpayments/__init__.py
switchpayments/SwitchPayments.py
switchpayments-0.1.0.dev1.dist-info/DESCRIPTION.rst
switchpayments-0.1.0.dev1.dist-info/METADATA
switchpayments-0.1.0.dev1.dist-info/metadata.json
switchpayments-0.1.0.dev1.dist-info/RECORD
switchpayments-0.1.0.dev1.dist-info/top_level.txt
switchpayments-0.1.0.dev1.dist-info/WHEEL
