Metadata-Version: 2.0
Name: switchpayments
Version: 0.1.0.dev1
Summary: SwitchPayments
Home-page: https://pypi.python.org/pypi/test_pypi
Author: The Switch. Team
Author-email: info@switchpayments.com
License: MIT
Keywords: payment payments
Platform: UNKNOWN
Classifier: Development Status :: 3 - Alpha
Classifier: Intended Audience :: Developers
Classifier: Topic :: Software Development :: Libraries
Classifier: License :: OSI Approved :: MIT License
Classifier: Programming Language :: Python :: 2
Classifier: Programming Language :: Python :: 2.6
Classifier: Programming Language :: Python :: 2.7
Classifier: Programming Language :: Python :: 3
Classifier: Programming Language :: Python :: 3.2
Classifier: Programming Language :: Python :: 3.3
Classifier: Programming Language :: Python :: 3.4
